CHANGELOG.md
LICENSE
README.md
asynch/__init__.py
asynch/connection.py
asynch/cursors.py
asynch/errors.py
asynch/pool.py
asynch/proto/__init__.py
asynch/proto/block.py
asynch/proto/columns/__init__.py
asynch/proto/columns/arraycolumn.py
asynch/proto/columns/base.py
asynch/proto/columns/boolcolumn.py
asynch/proto/columns/datecolumn.py
asynch/proto/columns/datetimecolumn.py
asynch/proto/columns/decimalcolumn.py
asynch/proto/columns/enumcolumn.py
asynch/proto/columns/floatcolumn.py
asynch/proto/columns/intcolumn.py
asynch/proto/columns/intervalcolumn.py
asynch/proto/columns/ipcolumn.py
asynch/proto/columns/jsoncolumn.py
asynch/proto/columns/lowcardinalitycolumn.py
asynch/proto/columns/mapcolumn.py
asynch/proto/columns/nestedcolumn.py
asynch/proto/columns/nothingcolumn.py
asynch/proto/columns/nullablecolumn.py
asynch/proto/columns/nullcolumn.py
asynch/proto/columns/simpleaggregatefunctioncolumn.py
asynch/proto/columns/stringcolumn.py
asynch/proto/columns/tuplecolumn.py
asynch/proto/columns/util.py
asynch/proto/columns/uuidcolumn.py
asynch/proto/compression/__init__.py
asynch/proto/compression/lz4.py
asynch/proto/compression/lz4hc.py
asynch/proto/compression/zstd.py
asynch/proto/connection.py
asynch/proto/constants.py
asynch/proto/context.py
asynch/proto/cs.py
asynch/proto/opentelemetry.py
asynch/proto/progress.py
asynch/proto/protocol.py
asynch/proto/result.py
asynch/proto/settings/__init__.py
asynch/proto/settings/available.py
asynch/proto/settings/types.py
asynch/proto/streams/__init__.py
asynch/proto/streams/block.py
asynch/proto/streams/buffered.py
asynch/proto/streams/compressed.py
asynch/proto/utils/__init__.py
asynch/proto/utils/compat.py
asynch/proto/utils/escape.py
asynch/proto/utils/helpers.py
asynch_lxneng-0.2.5.dist-info/LICENSE
asynch_lxneng-0.2.5.dist-info/METADATA
asynch_lxneng-0.2.5.dist-info/WHEEL
asynch_lxneng-0.2.5.dist-info/RECORD
